tests/__init__.py
tests/test_lib.py
tests/test_serialise.py
trustthedice/__init__.py
trustthedice/cli.py
trustthedice/exceptions.py
trustthedice/lib.py
trustthedice/serialise.py
trustthedice-0.0.2.dist-info/LICENSE
trustthedice-0.0.2.dist-info/METADATA
trustthedice-0.0.2.dist-info/WHEEL
trustthedice-0.0.2.dist-info/entry_points.txt
trustthedice-0.0.2.dist-info/top_level.txt
trustthedice-0.0.2.dist-info/RECORD
