Metadata-Version: 2.1
Name: trustthedice
Version: 0.0.2
Summary: Let random numbers rule your life!
Home-page: https://github.com/sujaymansingh/trustthedice
Author: Sujay Mansingh
Author-email: info@sujaymansingh.com
License: UNKNOWN
Platform: UNKNOWN
Classifier: Programming Language :: Python :: 3
Classifier: License :: OSI Approved :: MIT License
Classifier: Operating System :: OS Independent
Requires-Dist: attrs (==19.1.0)
Requires-Dist: black (==19.3b0)
Requires-Dist: Click (==7.0)
Requires-Dist: pytest (==4.4.1)
